set_proj_dir/__init__.py
set_proj_dir/find_dir.py
set_proj_dir/find_git_proj_dir.py
set_proj_dir/set_dir_in_path.py
set_proj_dir/set_proj_dir.py
setprojrootinpath-0.1.0.dist-info/LICENSE
setprojrootinpath-0.1.0.dist-info/METADATA
setprojrootinpath-0.1.0.dist-info/WHEEL
setprojrootinpath-0.1.0.dist-info/top_level.txt
setprojrootinpath-0.1.0.dist-info/RECORD
