Metadata-Version: 2.2
Name: SetProjRootinPath
Version: 0.1.0
Summary: Utilitario simples para colocar o diretorio do projeto no path do notebook. Ajuda a importar submodulos no notebook
Author-email: Henrique Pougy <hpougy@prefeitura.sp.gov.br>, Olivia Silva Amann <oliviaamann@prefeitura.sp.gov.br>
License:                     GNU AFFERO GENERAL PUBLIC LICENSE
Project-URL: Homepage, https://github.com/sepep-pmsp/configuracoes_notebooks
Project-URL: Bug Tracker, https://github.com/sepep-pmsp/configuracoes_notebooks/issues
License-File: LICENSE
